{"displayName": "PC Keyboard Braille Input (legacy)", "publisher": "NV Access Limited, Noelia Ruiz Mart\u00ednez <nrm1977@gmail.com>", "description": "Allows braille to be entered via the PC keyboard.", "addonId": "pckbbrl", "addonVersionName": "2023.02.23", "addonVersionNumber": {"major": 2023, "minor": 2, "patch": 23}, "minNVDAVersion": {"major": 2019, "minor": 3, "patch": 0}, "lastTestedVersion": {"major": 2023, "minor": 1, "patch": 0}, "channel": "stable", "URL": "https://github.com/nvdaes/pcKbBrl/releases/download/2023.02.23/pcKbBrl-2023.02.23.nvda-addon", "sha256": "e6daa7a9dc02944ddef666bc5283f797368ea89ef1a72b2586ef76e9670aad74", "sourceURL": "https://addons.nvda-project.org/", "license": "unknown"}